{
	"configurations" : 
	[
		{
			"directories" : 
			[
				{
					"build" : ".",
					"hasInstallRule" : true,
					"jsonFile" : "directory-.-Debug-4bd88f05264e87ec8f5c.json",
					"minimumCMakeVersion" : 
					{
						"string" : "3.16"
					},
					"projectIndex" : 0,
					"source" : ".",
					"targetIndexes" : 
					[
						0,
						1,
						2
					]
				}
			],
			"name" : "Debug",
			"projects" : 
			[
				{
					"directoryIndexes" : 
					[
						0
					],
					"name" : "RegistrationPage",
					"targetIndexes" : 
					[
						0,
						1,
						2
					]
				}
			],
			"targets" : 
			[
				{
					"directoryIndex" : 0,
					"id" : "RegistrationPage::@6890427a1f51a3e7e1df",
					"jsonFile" : "target-RegistrationPage-Debug-7697ecdca4ddb363f121.json",
					"name" : "RegistrationPage",
					"projectIndex" : 0
				},
				{
					"directoryIndex" : 0,
					"id" : "RegistrationPage_autogen::@6890427a1f51a3e7e1df",
					"jsonFile" : "target-RegistrationPage_autogen-Debug-9540c443362c512d2a49.json",
					"name" : "RegistrationPage_autogen",
					"projectIndex" : 0
				},
				{
					"directoryIndex" : 0,
					"id" : "RegistrationPage_autogen_timestamp_deps::@6890427a1f51a3e7e1df",
					"jsonFile" : "target-RegistrationPage_autogen_timestamp_deps-Debug-3ed139c8d2448da01964.json",
					"name" : "RegistrationPage_autogen_timestamp_deps",
					"projectIndex" : 0
				}
			]
		}
	],
	"kind" : "codemodel",
	"paths" : 
	{
		"build" : "C:/Users/Hp Victus/Desktop/qt practice/RegistrationPage/build/Desktop_Qt_6_8_0_MinGW_64_bit-Debug",
		"source" : "C:/Users/Hp Victus/Desktop/qt practice/RegistrationPage"
	},
	"version" : 
	{
		"major" : 2,
		"minor" : 7
	}
}
